waifu_scorer/__init__.py
waifu_scorer/__main__.py
waifu_scorer/mlp.py
waifu_scorer/predict.py
waifu_scorer/py.typed
waifu_scorer-0.2.1.dist-info/METADATA
waifu_scorer-0.2.1.dist-info/WHEEL
waifu_scorer-0.2.1.dist-info/licenses/LICENSE
waifu_scorer-0.2.1.dist-info/RECORD
