Metadata-Version: 2.4
Name: waifu-scorer
Version: 0.2.1
Summary: A deep learning-based tool for scoring anime-style (waifu) images, supporting multiple hardware backends and PyTorch environments.
Project-URL: Homepage, https://github.com/jannchie/waifu-scorer
Project-URL: Repository, https://github.com/jannchie/waifu-scorer
Project-URL: Documentation, https://github.com/jannchie/waifu-scorer#readme
Project-URL: Bug Tracker, https://github.com/jannchie/waifu-scorer/issues
Project-URL: Reference, https://github.com/Eugeoter/waifuset
Author-email: Jianqi Pan <jannchie@gmail.com>
License: MPL-2.0
License-File: LICENSE
Keywords: AI,deep learning,image analysis,scoring,waifu
Classifier: Intended Audience :: Developers
Classifier: License :: OSI Approved :: Mozilla Public License 2.0 (MPL 2.0)
Classifier: Operating System :: OS Independent
Classifier: Programming Language :: Python :: 3
Classifier: Topic :: Scientific/Engineering :: Artificial Intelligence
Requires-Python: >=3.10
Requires-Dist: clip>=0.2.0
Requires-Dist: huggingface-hub>=0.32.3
Requires-Dist: numpy>=2.2.6
Requires-Dist: pillow>=11.2.1
Requires-Dist: safetensors>=0.5.3
Requires-Dist: transformers>=4.52.4
Provides-Extra: cpu
Requires-Dist: torch>=2.5.1; extra == 'cpu'
Provides-Extra: cu121
Requires-Dist: torch>=2.5.1; extra == 'cu121'
Provides-Extra: cu124
Requires-Dist: torch>=2.6.0; extra == 'cu124'
